README
setup.py
cmdparse/__init__.py
cmdparse/cmdparse.py
cmdparse.egg-info/PKG-INFO
cmdparse.egg-info/SOURCES.txt
cmdparse.egg-info/dependency_links.txt
cmdparse.egg-info/top_level.txt