Metadata-Version: 1.0
Name: cmdparse
Version: 0.9
Summary: A command line parser for CVS-style subcommands
Home-page: http://wiki.github.com/pteichman/python-cmdparse/
Author: Peter Teichman
Author-email: peter@teichman.org
License: UNKNOWN
Download-URL: http://github.com/pteichman/python-cmdparse/downloads
Platform: UNKNOWN
Classifier: Programming Language :: Python
Classifier: License :: OSI Approved :: MIT License
Classifier: Operating System :: OS Independent
Classifier: Development Status :: 5 - Production/Stable
Classifier: Intended Audience :: Developers
Classifier: Topic :: Software Development :: User Interfaces
